my_module/__init__.py
my_module/functions.py
tests/__init__.py
tests/test_functions.py
funny_gpt_stuytowners-0.0.3.dist-info/LICENSE
funny_gpt_stuytowners-0.0.3.dist-info/METADATA
funny_gpt_stuytowners-0.0.3.dist-info/WHEEL
funny_gpt_stuytowners-0.0.3.dist-info/top_level.txt
funny_gpt_stuytowners-0.0.3.dist-info/RECORD
