Metadata-Version: 2.1
Name: funny-gpt-stuytowners
Version: 0.0.3
Summary: A package for project 3 for stuytowners
Author-email: Example Author <author@example.com>
Project-URL: Homepage, https://github.com/software-students-fall2023/3-python-package-exercise-stuytowners/tree/main
Classifier: Programming Language :: Python :: 3
Classifier: License :: OSI Approved :: MIT License
Classifier: Operating System :: OS Independent
Requires-Python: >=3.7
License-File: LICENSE
